sgroove/__init__.py
sgroove/ansistring.py
sgroove/ansistring.pyi
sgroove/color.py
sgroove/modifier.py
sgroove/presets.py
sgroove/py.typed
sgroove/style.py
sgroove-0.1.0.dist-info/WHEEL
sgroove-0.1.0.dist-info/METADATA
sgroove-0.1.0.dist-info/RECORD
