Metadata-Version: 2.3
Name: sgroove
Version: 0.1.0
Summary: Fluent ANSI-styled strings for Python.
Keywords: ansi,sgr,terminal,formatting,text-style,color
Author: Lukas Schulig
Author-email: Lukas Schulig <schuligl@uni-greifswald.de>
Classifier: Development Status :: 4 - Beta
Classifier: License :: OSI Approved :: MIT License
Classifier: Environment :: Console
Classifier: Programming Language :: Python :: 3
Classifier: Programming Language :: Python :: 3 :: Only
Classifier: Topic :: Utilities
Classifier: Topic :: Text Processing
Classifier: Topic :: Software Development :: Libraries :: Python Modules
Classifier: Typing :: Typed
Requires-Python: >=3.14
